snntorch/__init__.py
snntorch/_version.py
snntorch/backprop.py
snntorch/spikegen.py
snntorch/spikeplot.py
snntorch/surrogate.py
snntorch/utils.py
snntorch/_neurons/__init__.py
snntorch/_neurons/alpha.py
snntorch/_neurons/lapicque.py
snntorch/_neurons/leaky.py
snntorch/_neurons/neurons.py
snntorch/_neurons/rleaky.py
snntorch/_neurons/rsynaptic.py
snntorch/_neurons/sconv2dlstm.py
snntorch/_neurons/slstm.py
snntorch/_neurons/synaptic.py
snntorch/custom_ops/Makefile
snntorch/custom_ops/fast_sigmoid.cpp
snntorch/custom_ops/heaviside_custom_op.cpp
snntorch/custom_ops/straight_through_estimator.cpp
snntorch/functional/__init__.py
snntorch/functional/acc.py
snntorch/functional/loss.py
snntorch/functional/quant.py
snntorch/functional/reg.py
snntorch/so_file/__init__.py
snntorch/spikevision/__init__.py
snntorch/spikevision/_transforms.py
snntorch/spikevision/_utils.py
snntorch/spikevision/events_timeslices.py
snntorch/spikevision/neuromorphic_dataset.py
snntorch/spikevision/spikedata/__init__.py
snntorch/spikevision/spikedata/dvs_gesture.py
snntorch/spikevision/spikedata/nmnist.py
snntorch/spikevision/spikedata/shd.py
snntorch_ipu-0.5.18.dist-info/LICENSE
snntorch_ipu-0.5.18.dist-info/METADATA
snntorch_ipu-0.5.18.dist-info/WHEEL
snntorch_ipu-0.5.18.dist-info/top_level.txt
snntorch_ipu-0.5.18.dist-info/RECORD
