Metadata-Version: 2.1
Name: snntorch-ipu
Version: 0.5.18
Summary: Deep learning with spiking neural networks on IPUs.
Home-page: https://github.com/vinniesun/snntorch-ipu
Author: Jason K. Eshraghian & Vincent Sun
Author-email: jasonesh@umich.edu
License: GNU General Public License v3
Keywords: snntorch
Platform: UNKNOWN
Classifier: Development Status :: 2 - Pre-Alpha
Classifier: Intended Audience :: Developers
Classifier: Intended Audience :: Education
Classifier: Intended Audience :: Science/Research
Classifier: License :: OSI Approved :: GNU General Public License v3 (GPLv3)
Classifier: Natural Language :: English
Classifier: Topic :: Scientific/Engineering
Classifier: Topic :: Scientific/Engineering :: Mathematics
Classifier: Topic :: Scientific/Engineering :: Artificial Intelligence
Classifier: Topic :: Scientific/Engineering :: Bio-Informatics
Classifier: Programming Language :: Python :: 3.6
Classifier: Programming Language :: Python :: 3.7
Classifier: Programming Language :: Python :: 3.8
Classifier: Operating System :: OS Independent
Requires-Python: >=3.6
License-File: LICENSE
Requires-Dist: torch (>=1.1.0)
Requires-Dist: pandas
Requires-Dist: matplotlib
Requires-Dist: numpy (>=1.17)
